{
  "openapi": "3.1.1",
  "info": {
    "title": "praktyki | v1",
    "version": "1.0.0"
  },
  "servers": [
    {
      "url": "https://localhost:7012"
    },
    {
      "url": "http://localhost:5020"
    }
  ],
  "paths": {
    "/api/VerifyVies/{countryCode}/vat/{taxId}": {
      "get": {
        "tags": [
          "VerifyVies"
        ],
        "parameters": [
          {
            "name": "countryCode",
            "in": "path",
            "required": true,
            "schema": {
              "type": "string"
            }
          },
          {
            "name": "taxId",
            "in": "path",
            "required": true,
            "schema": {
              "type": "string"
            }
          }
        ],
        "responses": {
          "200": {
            "description": "OK"
          }
        }
      }
    },
    "/api/Clients": {
      "get": {
        "tags": [
          "Clients"
        ],
        "responses": {
          "200": {
            "description": "OK",
            "content": {
              "text/plain": {
                "schema": {
                  "type": "array",
                  "items": {
                    "$ref": "#/components/schemas/Client"
                  }
                }
              },
              "application/json": {
                "schema": {
                  "type": "array",
                  "items": {
                    "$ref": "#/components/schemas/Client"
                  }
                }
              },
              "text/json": {
                "schema": {
                  "type": "array",
                  "items": {
                    "$ref": "#/components/schemas/Client"
                  }
                }
              }
            }
          }
        }
      },
      "post": {
        "tags": [
          "Clients"
        ],
        "requestBody": {
          "content": {
            "application/json": {
              "schema": {
                "$ref": "#/components/schemas/Client"
              }
            },
            "text/json": {
              "schema": {
                "$ref": "#/components/schemas/Client"
              }
            },
            "application/*+json": {
              "schema": {
                "$ref": "#/components/schemas/Client"
              }
            }
          },
          "required": true
        },
        "responses": {
          "200": {
            "description": "OK",
            "content": {
              "text/plain": {
                "schema": {
                  "$ref": "#/components/schemas/Client"
                }
              },
              "application/json": {
                "schema": {
                  "$ref": "#/components/schemas/Client"
                }
              },
              "text/json": {
                "schema": {
                  "$ref": "#/components/schemas/Client"
                }
              }
            }
          }
        }
      }
    },
    "/api/Clients/{id}": {
      "delete": {
        "tags": [
          "Clients"
        ],
        "parameters": [
          {
            "name": "id",
            "in": "path",
            "required": true,
            "schema": {
              "pattern": "^-?(?:0|[1-9]\\d*)$",
              "type": [
                "integer",
                "string"
              ],
              "format": "int32"
            }
          }
        ],
        "responses": {
          "200": {
            "description": "OK"
          }
        }
      },
      "put": {
        "tags": [
          "Clients"
        ],
        "parameters": [
          {
            "name": "id",
            "in": "path",
            "required": true,
            "schema": {
              "pattern": "^-?(?:0|[1-9]\\d*)$",
              "type": [
                "integer",
                "string"
              ],
              "format": "int32"
            }
          }
        ],
        "requestBody": {
          "content": {
            "application/json": {
              "schema": {
                "$ref": "#/components/schemas/Client"
              }
            },
            "text/json": {
              "schema": {
                "$ref": "#/components/schemas/Client"
              }
            },
            "application/*+json": {
              "schema": {
                "$ref": "#/components/schemas/Client"
              }
            }
          },
          "required": true
        },
        "responses": {
          "200": {
            "description": "OK"
          }
        }
      }
    },
    "/api/VerifyPesel/{peselInput}": {
      "get": {
        "tags": [
          "VerifyPesel"
        ],
        "parameters": [
          {
            "name": "peselInput",
            "in": "path",
            "required": true,
            "schema": {
              "type": "string"
            }
          }
        ],
        "responses": {
          "200": {
            "description": "OK",
            "content": {
              "text/plain": {
                "schema": {
                  "$ref": "#/components/schemas/VerifyPeselResponse"
                }
              },
              "application/json": {
                "schema": {
                  "$ref": "#/components/schemas/VerifyPeselResponse"
                }
              },
              "text/json": {
                "schema": {
                  "$ref": "#/components/schemas/VerifyPeselResponse"
                }
              }
            }
          }
        }
      }
    }
  },
  "components": {
    "schemas": {
      "Client": {
        "type": "object",
        "properties": {
          "id": {
            "pattern": "^-?(?:0|[1-9]\\d*)$",
            "type": [
              "integer",
              "string"
            ],
            "format": "int32"
          },
          "isCompany": {
            "type": "boolean"
          },
          "nip": {
            "type": [
              "null",
              "string"
            ]
          },
          "pesel": {
            "type": [
              "null",
              "string"
            ]
          },
          "firstname": {
            "type": [
              "null",
              "string"
            ]
          },
          "lastname": {
            "type": [
              "null",
              "string"
            ]
          },
          "name": {
            "type": "string"
          },
          "country": {
            "type": [
              "null",
              "string"
            ]
          }
        }
      },
      "VerifyPeselResponse": {
        "type": "object",
        "properties": {
          "isValid": {
            "type": "boolean"
          },
          "birthDate": {
            "type": [
              "null",
              "string"
            ]
          },
          "gender": {
            "type": [
              "null",
              "string"
            ]
          },
          "message": {
            "type": [
              "null",
              "string"
            ]
          }
        }
      }
    }
  },
  "tags": [
    {
      "name": "VerifyVies"
    },
    {
      "name": "Clients"
    },
    {
      "name": "VerifyPesel"
    }
  ]
}